hello_felicette1963_docker-0.2.0.dist-info/METADATA
hello_felicette1963_docker-0.2.0.dist-info/WHEEL
hello_felicette1963_docker/__init__.py
hello_felicette1963_docker/who.py
hello_felicette1963_docker-0.2.0.dist-info/RECORD
