Metadata-Version: 2.1
Name: hello-Felicette1963-Docker
Version: 0.2.0
Summary: The Python program
Author-Email: Felicette1963 <xorudlee4869@gmail.com>
License: MIT
Requires-Python: >=3.8
